pydantic_outputs/__init__.py
pydantic_outputs/structured_output.py
pydantic_outputs-0.1.2.dist-info/METADATA
pydantic_outputs-0.1.2.dist-info/WHEEL
pydantic_outputs-0.1.2.dist-info/top_level.txt
pydantic_outputs-0.1.2.dist-info/RECORD
